{
  "meta": {
    "version": "2026-04",
    "region": "La Réunion",
    "generated": "2026-04-07",
    "commune": "Bras-Panon",
    "insee": "97402",
    "intercommunalite": "CIREST",
    "plu_type": "PLU",
    "plu_date_approbation": "2021-10-20",
    "source": "GPU DU_97402"
  },
  "zones": {
    "UA": {
      "label": "Centre-bourg",
      "type": "U",
      "sous_type": "centre_urbain",
      "reculs": {
        "voie_principale_m": 2,
        "voie_rn_hors_agglo_axe_m": 75,
        "sep_lat_m": 3,
        "sep_lat_limite_autorisee": true,
        "sep_fond_m": 3,
        "inter_batiments_m": 4
      },
      "emprise": {
        "emprise_sol_max_pct": 70
      },
      "permeabilite": {
        "permeable_min_pct": 30
      },
      "_meta": {
        "confidence": 0.8,
        "ambiguites": [
          "Hauteur UA non trouvée"
        ]
      }
    },
    "UB": {
      "label": "Résidentiel intermédiaire",
      "type": "U",
      "reculs": {
        "voie_principale_m": 4,
        "voie_rn_hors_agglo_axe_m": 75,
        "sep_lat_m": 3,
        "sep_fond_m": 3,
        "inter_batiments_m": 4
      },
      "hauteurs": {
        "he_voie_m": 6,
        "he_arriere_m": 9,
        "annexe_hf_max_m": 3.5
      },
      "emprise": {
        "emprise_sol_max_pct": 60
      },
      "permeabilite": {
        "permeable_min_pct": 30
      },
      "_meta": {
        "confidence": 1,
        "ambiguites": []
      }
    },
    "UC": {
      "label": "Résidentiel diffus",
      "type": "U",
      "reculs": {
        "voie_principale_m": 4,
        "voie_rn_hors_agglo_axe_m": 75,
        "sep_lat_m": 3,
        "sep_fond_m": 3,
        "inter_batiments_m": 4
      },
      "emprise": {
        "emprise_sol_max_pct": 50
      },
      "permeabilite": {
        "permeable_min_pct": 30
      },
      "_meta": {
        "confidence": 0.8,
        "ambiguites": [
          "Hauteur UC non trouvée"
        ]
      }
    },
    "UD": {
      "label": "Résidentiel rural",
      "type": "U",
      "reculs": {
        "voie_principale_m": 4,
        "voie_rn_hors_agglo_axe_m": 75,
        "sep_lat_m": 3,
        "sep_fond_m": 3,
        "inter_batiments_m": 4
      },
      "emprise": {
        "emprise_sol_max_pct": 50
      },
      "permeabilite": {
        "permeable_min_pct": 40
      },
      "_meta": {
        "confidence": 0.8,
        "ambiguites": [
          "Hauteur UD non trouvée"
        ]
      }
    },
    "UE": {
      "label": "Activités",
      "type": "U",
      "sous_type": "activites",
      "reculs": {
        "voie_principale_m": 5,
        "voie_rn_hors_agglo_axe_m": 75,
        "sep_lat_m": 5,
        "sep_fond_m": 5
      },
      "emprise": {
        "emprise_sol_max_pct": 50
      },
      "permeabilite": {
        "permeable_min_pct": 20
      },
      "_meta": {
        "confidence": 0.8,
        "ambiguites": [
          "Hauteur UE non trouvée"
        ]
      }
    },
    "AU": {
      "label": "Zones AU",
      "type": "AU",
      "ref": "zone U",
      "zones_speciales": {
        "AUec": {
          "hf_max_m": 18,
          "permeable_min_pct": 15
        }
      },
      "_meta": {
        "confidence": 1,
        "ambiguites": []
      }
    },
    "AUst": {
      "label": "AU strict",
      "type": "AU",
      "sous_type": "strict",
      "construction_neuve_interdite": true,
      "_meta": {
        "confidence": 1,
        "ambiguites": []
      }
    },
    "A": {
      "label": "Agricole",
      "type": "A",
      "reculs": {
        "voie_principale_m": 4,
        "sep_lat_m": 5
      },
      "hauteurs": {
        "he_max_m": 4,
        "hf_max_m": 7
      },
      "_meta": {
        "confidence": 1,
        "ambiguites": []
      }
    },
    "N": {
      "label": "Naturelle",
      "type": "N",
      "reculs": {
        "voie_principale_m": 4,
        "sep_lat_m": 5
      },
      "hauteurs": {
        "he_max_m": 4,
        "hf_max_m": 7
      },
      "_meta": {
        "confidence": 1,
        "ambiguites": []
      }
    }
  },
  "regles_communes": {
    "ravine_recul_m": 10,
    "voie_rn_hors_agglo_axe_m": 75,
    "cloture_voie_hauteur_max_m": 2,
    "rtaa_dom": "2016"
  }
}